{"id":"click._compat","path":"/Users/henrycooper/Documents/GitHub/HomelessAid/test_env/lib/python3.11/site-packages/click/_compat.py","mtime":1715106500,"size":18744,"hash":"e77d7c6a04296ede24ae82ac6ea0ce6294d25b32ff6026555108934f4e325e67","data_mtime":1714951656,"dependencies":["codecs","io","os","re","sys","typing","weakref","builtins","abc","enum","typing_extensions"],"suppressed":[],"options":{"extra_checks":false,"follow_imports":"normal","disallow_any_explicit":false,"plugins":[],"implicit_reexport":true,"follow_imports_for_stubs":false,"disable_error_code":[],"disable_memoryview_promotion":false,"check_untyped_defs":false,"disallow_untyped_defs":false,"disallow_any_unimported":false,"new_type_inference":false,"disallow_untyped_decorators":false,"local_partial_types":false,"warn_unused_ignores":false,"allow_untyped_globals":false,"disallow_any_expr":false,"mypyc":false,"bazel":false,"platform":"darwin","warn_unreachable":false,"ignore_missing_imports":false,"allow_redefinition":false,"strict_optional":true,"disallow_untyped_calls":false,"strict_concatenate":false,"disable_bytearray_promotion":false,"strict_equality":false,"disallow_any_decorated":false,"enable_error_code":[],"ignore_errors":false,"warn_return_any":false,"implicit_optional":false,"disallow_any_generics":false,"enabled_error_codes":[],"disallow_incomplete_defs":false,"always_true":[],"always_false":[],"warn_no_return":true,"disabled_error_codes":[],"disallow_subclassing_any":false},"dep_prios":[10,10,10,10,10,10,5,5,30,30,30],"dep_lines":[1,2,3,4,5,6,7,1,1,1,1],"interface_hash":"0cb404aab198c41469ea1d9a3d5c687933273be66077fc7234119d816c002a3a","version_id":"1.6.1","ignore_all":true,"plugin_data":null}